[
  {
    "id": "102",
    "name": "Kevin Bacon",
    "birth": "1958"
  },
  {
    "id": "129",
    "name": "Tom Cruise",
    "birth": "1962"
  },
  {
    "id": "144",
    "name": "Cary Elwes",
    "birth": "1962"
  },
  {
    "id": "158",
    "name": "Tom Hanks",
    "birth": "1956"
  },
  {
    "id": "1597",
    "name": "Mandy Patinkin",
    "birth": "1952"
  },
  {
    "id": "163",
    "name": "Dustin Hoffman",
    "birth": "1937"
  },
  {
    "id": "1697",
    "name": "Chris Sarandon",
    "birth": "1942"
  },
  {
    "id": "193",
    "name": "Demi Moore",
    "birth": "1962"
  },
  {
    "id": "197",
    "name": "Jack Nicholson",
    "birth": "1937"
  },
  {
    "id": "200",
    "name": "Bill Paxton",
    "birth": "1955"
  },
  {
    "id": "398",
    "name": "Sally Field",
    "birth": "1946"
  },
  {
    "id": "420",
    "name": "Valeria Golino",
    "birth": "1965"
  },
  {
    "id": "596520",
    "name": "Gerald R. Molen",
    "birth": "1935"
  },
  {
    "id": "641",
    "name": "Gary Sinise",
    "birth": "1955"
  },
  {
    "id": "705",
    "name": "Robin Wright",
    "birth": "1966"
  },
  {
    "id": "914612",
    "name": "Emma Watson",
    "birth": "1990"
  }
]